{
  "openapi": "3.1.0",
  "info": {
    "title": "Beyond Auth",
    "description": "Per-project authentication and authorization service.",
    "license": {
      "name": "AGPL-3.0",
      "identifier": "AGPL-3.0"
    },
    "version": "1"
  },
  "paths": {
    "/healthz": {
      "get": {
        "tags": ["system"],
        "operationId": "healthz",
        "responses": {
          "200": {
            "description": "",
            "content": {
              "application/json": {
                "schema": {
                  "$ref": "#/components/schemas/HealthzResponse"
                }
              }
            }
          },
          "503": {
            "description": "",
            "content": {
              "application/json": {
                "schema": {
                  "$ref": "#/components/schemas/HealthzResponse"
                }
              }
            }
          }
        }
      }
    },
    "/v1/admin/relation-partitions/{object_type}": {
      "put": {
        "tags": ["admin"],
        "summary": "Ensure a dedicated LIST partition exists for `object_type`.",
        "description": "Idempotent — safe to call multiple times. Existing rows in the default\npartition are moved to the new partition atomically.",
        "operationId": "ensure_partition",
        "parameters": [
          {
            "name": "object_type",
            "in": "path",
            "description": "Object type to partition (e.g. \"document\")",
            "required": true,
            "schema": {
              "type": "string"
            }
          }
        ],
        "responses": {
          "204": {
            "description": "Partition exists (created or already present)"
          },
          "422": {
            "description": "Invalid object_type identifier",
            "content": {
              "application/json": {
                "schema": {
                  "$ref": "#/components/schemas/ErrorResponse"
                }
              }
            }
          }
        }
      }
    },
    "/v1/authz/decisions": {
      "get": {
        "tags": ["authz"],
        "summary": "Check whether the current session user (or an explicit user) has a permission\non a resource. Uses a bundled session-validation + authz CTE for one DB round-trip\nwhen checking the current session user.",
        "operationId": "check_permission",
        "parameters": [
          {
            "name": "user",
            "in": "query",
            "description": "Explicit subject to check as. Defaults to the current session user.",
            "required": false,
            "schema": {
              "type": ["string", "null"]
            }
          },
          {
            "name": "permission",
            "in": "query",
            "required": true,
            "schema": {
              "type": "string"
            }
          },
          {
            "name": "resource_type",
            "in": "query",
            "required": true,
            "schema": {
              "type": "string"
            }
          },
          {
            "name": "resource_id",
            "in": "query",
            "required": true,
            "schema": {
              "type": "string"
            }
          }
        ],
        "responses": {
          "200": {
            "description": "",
            "content": {
              "application/json": {
                "schema": {
                  "$ref": "#/components/schemas/CheckResponse"
                }
              }
            }
          },
          "400": {
            "description": "Authz not enabled",
            "content": {
              "application/json": {
                "schema": {
                  "$ref": "#/components/schemas/ErrorResponse"
                }
              }
            }
          },
          "401": {
            "description": "Unauthorized",
            "content": {
              "application/json": {
                "schema": {
                  "$ref": "#/components/schemas/ErrorResponse"
                }
              }
            }
          },
          "422": {
            "description": "Unknown resource/permission",
            "content": {
              "application/json": {
                "schema": {
                  "$ref": "#/components/schemas/ErrorResponse"
                }
              }
            }
          }
        }
      }
    },
    "/v1/authz/expansions": {
      "get": {
        "tags": ["authz"],
        "summary": "Expand a relation: return all subjects who hold the given relation on the object.\nResolves subject sets recursively.",
        "operationId": "expand_relation",
        "parameters": [
          {
            "name": "object_type",
            "in": "query",
            "required": true,
            "schema": {
              "type": "string"
            }
          },
          {
            "name": "object_id",
            "in": "query",
            "required": true,
            "schema": {
              "type": "string"
            }
          },
          {
            "name": "relation",
            "in": "query",
            "required": true,
            "schema": {
              "type": "string"
            }
          }
        ],
        "responses": {
          "200": {
            "description": "",
            "content": {
              "application/json": {
                "schema": {
                  "$ref": "#/components/schemas/ExpandResponse"
                }
              }
            }
          },
          "400": {
            "description": "Authz not enabled",
            "content": {
              "application/json": {
                "schema": {
                  "$ref": "#/components/schemas/ErrorResponse"
                }
              }
            }
          }
        }
      }
    },
    "/v1/authz/lookups": {
      "get": {
        "tags": ["authz"],
        "summary": "List all objects of the given type that the current user (or an explicit user)\ncan access via the resolved roles for a permission. Includes both direct role\nassignments and access granted via parent hierarchy.",
        "operationId": "lookup_objects",
        "parameters": [
          {
            "name": "user",
            "in": "query",
            "required": false,
            "schema": {
              "type": ["string", "null"]
            }
          },
          {
            "name": "permission",
            "in": "query",
            "required": true,
            "schema": {
              "type": "string"
            }
          },
          {
            "name": "resource_type",
            "in": "query",
            "required": true,
            "schema": {
              "type": "string"
            }
          },
          {
            "name": "limit",
            "in": "query",
            "required": false,
            "schema": {
              "type": "integer",
              "format": "int64"
            }
          },
          {
            "name": "cursor",
            "in": "query",
            "required": false,
            "schema": {
              "type": ["string", "null"]
            }
          }
        ],
        "responses": {
          "200": {
            "description": "",
            "content": {
              "application/json": {
                "schema": {
                  "$ref": "#/components/schemas/LookupResponse"
                }
              }
            }
          },
          "400": {
            "description": "Authz not enabled",
            "content": {
              "application/json": {
                "schema": {
                  "$ref": "#/components/schemas/ErrorResponse"
                }
              }
            }
          },
          "422": {
            "description": "Unknown resource/permission",
            "content": {
              "application/json": {
                "schema": {
                  "$ref": "#/components/schemas/ErrorResponse"
                }
              }
            }
          }
        },
        "security": [
          {
            "BearerAuth": []
          }
        ]
      }
    },
    "/v1/authz/relations": {
      "post": {
        "tags": ["authz"],
        "summary": "Write a single relation tuple. Idempotent — duplicate writes are silently ignored.",
        "operationId": "write_relation",
        "requestBody": {
          "content": {
            "application/json": {
              "schema": {
                "$ref": "#/components/schemas/RelationRequest"
              }
            }
          },
          "required": true
        },
        "responses": {
          "201": {
            "description": "Relation written"
          },
          "400": {
            "description": "Authz not enabled",
            "content": {
              "application/json": {
                "schema": {
                  "$ref": "#/components/schemas/ErrorResponse"
                }
              }
            }
          }
        }
      },
      "delete": {
        "tags": ["authz"],
        "summary": "Delete a single relation tuple.",
        "operationId": "delete_relation",
        "requestBody": {
          "content": {
            "application/json": {
              "schema": {
                "$ref": "#/components/schemas/RelationRequest"
              }
            }
          },
          "required": true
        },
        "responses": {
          "204": {
            "description": "Relation deleted"
          },
          "400": {
            "description": "Authz not enabled",
            "content": {
              "application/json": {
                "schema": {
                  "$ref": "#/components/schemas/ErrorResponse"
                }
              }
            }
          },
          "404": {
            "description": "Relation not found",
            "content": {
              "application/json": {
                "schema": {
                  "$ref": "#/components/schemas/ErrorResponse"
                }
              }
            }
          }
        }
      },
      "patch": {
        "tags": ["authz"],
        "summary": "Batch write and/or delete relation tuples in a single transaction.",
        "operationId": "batch_relations",
        "requestBody": {
          "content": {
            "application/json": {
              "schema": {
                "$ref": "#/components/schemas/BatchRequest"
              }
            }
          },
          "required": true
        },
        "responses": {
          "200": {
            "description": "",
            "content": {
              "application/json": {
                "schema": {
                  "$ref": "#/components/schemas/BatchResponse"
                }
              }
            }
          },
          "400": {
            "description": "Authz not enabled",
            "content": {
              "application/json": {
                "schema": {
                  "$ref": "#/components/schemas/ErrorResponse"
                }
              }
            }
          }
        }
      }
    },
    "/v1/authz/schema": {
      "get": {
        "tags": ["authz"],
        "summary": "Get the current authz schema. Returns null if authz is not enabled.",
        "operationId": "get_schema",
        "responses": {
          "200": {
            "description": "",
            "content": {
              "application/json": {
                "schema": {
                  "oneOf": [
                    {
                      "type": "null"
                    },
                    {
                      "$ref": "#/components/schemas/AuthzSchema"
                    }
                  ]
                }
              }
            }
          }
        }
      },
      "put": {
        "tags": ["authz"],
        "summary": "Replace the authz schema. Validates and compiles before persisting.\nSetting schema to a valid document enables authz; this is the only way to enable it.",
        "operationId": "put_schema",
        "requestBody": {
          "content": {
            "application/json": {
              "schema": {
                "$ref": "#/components/schemas/AuthzSchema"
              }
            }
          },
          "required": true
        },
        "responses": {
          "200": {
            "description": "",
            "content": {
              "application/json": {
                "schema": {
                  "$ref": "#/components/schemas/AuthzSchema"
                }
              }
            }
          },
          "422": {
            "description": "Schema invalid",
            "content": {
              "application/json": {
                "schema": {
                  "$ref": "#/components/schemas/ErrorResponse"
                }
              }
            }
          }
        }
      }
    },
    "/v1/authz/traces": {
      "get": {
        "tags": ["authz"],
        "summary": "Explain why a permission check returned its result. Runs expand on all direct\nrole relations and reports which subjects appear, letting you trace a grant or\ndenial. Note: access granted purely via parent hierarchy is not reflected here.",
        "operationId": "why_check",
        "parameters": [
          {
            "name": "user",
            "in": "query",
            "required": true,
            "schema": {
              "type": "string"
            }
          },
          {
            "name": "permission",
            "in": "query",
            "required": true,
            "schema": {
              "type": "string"
            }
          },
          {
            "name": "resource_type",
            "in": "query",
            "required": true,
            "schema": {
              "type": "string"
            }
          },
          {
            "name": "resource_id",
            "in": "query",
            "required": true,
            "schema": {
              "type": "string"
            }
          }
        ],
        "responses": {
          "200": {
            "description": "",
            "content": {
              "application/json": {
                "schema": {
                  "$ref": "#/components/schemas/TraceResponse"
                }
              }
            }
          },
          "400": {
            "description": "Authz not enabled",
            "content": {
              "application/json": {
                "schema": {
                  "$ref": "#/components/schemas/ErrorResponse"
                }
              }
            }
          },
          "422": {
            "description": "Unknown resource/permission",
            "content": {
              "application/json": {
                "schema": {
                  "$ref": "#/components/schemas/ErrorResponse"
                }
              }
            }
          }
        }
      }
    },
    "/v1/emails": {
      "get": {
        "tags": ["emails"],
        "operationId": "list_emails",
        "responses": {
          "200": {
            "description": "",
            "content": {
              "application/json": {
                "schema": {
                  "type": "array",
                  "items": {
                    "$ref": "#/components/schemas/EmailRecord"
                  }
                }
              }
            }
          },
          "401": {
            "description": "",
            "content": {
              "application/json": {
                "schema": {
                  "$ref": "#/components/schemas/ErrorResponse"
                }
              }
            }
          }
        },
        "security": [
          {
            "BearerAuth": []
          }
        ]
      },
      "post": {
        "tags": ["emails"],
        "operationId": "add",
        "requestBody": {
          "content": {
            "application/json": {
              "schema": {
                "$ref": "#/components/schemas/AddRequest"
              }
            }
          },
          "required": true
        },
        "responses": {
          "200": {
            "description": "",
            "content": {
              "application/json": {
                "schema": {
                  "$ref": "#/components/schemas/OttTokenResponse"
                }
              }
            }
          },
          "401": {
            "description": "",
            "content": {
              "application/json": {
                "schema": {
                  "$ref": "#/components/schemas/ErrorResponse"
                }
              }
            }
          },
          "409": {
            "description": "Email already registered",
            "content": {
              "application/json": {
                "schema": {
                  "$ref": "#/components/schemas/ErrorResponse"
                }
              }
            }
          }
        },
        "security": [
          {
            "BearerAuth": []
          }
        ]
      }
    },
    "/v1/emails/verifications": {
      "post": {
        "tags": ["emails"],
        "operationId": "confirm_verification",
        "requestBody": {
          "content": {
            "application/json": {
              "schema": {
                "$ref": "#/components/schemas/ConfirmVerificationRequest"
              }
            }
          },
          "required": true
        },
        "responses": {
          "200": {
            "description": "",
            "content": {
              "application/json": {
                "schema": {
                  "$ref": "#/components/schemas/ConfirmVerificationResponse"
                }
              }
            }
          },
          "401": {
            "description": "Invalid or expired token",
            "content": {
              "application/json": {
                "schema": {
                  "$ref": "#/components/schemas/ErrorResponse"
                }
              }
            }
          },
          "404": {
            "description": "",
            "content": {
              "application/json": {
                "schema": {
                  "$ref": "#/components/schemas/ErrorResponse"
                }
              }
            }
          }
        }
      }
    },
    "/v1/emails/{id}": {
      "put": {
        "tags": ["emails"],
        "operationId": "make_primary",
        "parameters": [
          {
            "name": "id",
            "in": "path",
            "description": "Email ID",
            "required": true,
            "schema": {
              "type": "string",
              "format": "uuid"
            }
          }
        ],
        "responses": {
          "204": {
            "description": "Email set as primary"
          },
          "401": {
            "description": "",
            "content": {
              "application/json": {
                "schema": {
                  "$ref": "#/components/schemas/ErrorResponse"
                }
              }
            }
          },
          "404": {
            "description": "Email not found or not verified",
            "content": {
              "application/json": {
                "schema": {
                  "$ref": "#/components/schemas/ErrorResponse"
                }
              }
            }
          }
        },
        "security": [
          {
            "BearerAuth": []
          }
        ]
      },
      "delete": {
        "tags": ["emails"],
        "operationId": "remove",
        "parameters": [
          {
            "name": "id",
            "in": "path",
            "description": "Email ID",
            "required": true,
            "schema": {
              "type": "string",
              "format": "uuid"
            }
          }
        ],
        "responses": {
          "204": {
            "description": "Email removed"
          },
          "401": {
            "description": "",
            "content": {
              "application/json": {
                "schema": {
                  "$ref": "#/components/schemas/ErrorResponse"
                }
              }
            }
          },
          "404": {
            "description": "",
            "content": {
              "application/json": {
                "schema": {
                  "$ref": "#/components/schemas/ErrorResponse"
                }
              }
            }
          },
          "409": {
            "description": "Cannot remove primary email",
            "content": {
              "application/json": {
                "schema": {
                  "$ref": "#/components/schemas/ErrorResponse"
                }
              }
            }
          }
        },
        "security": [
          {
            "BearerAuth": []
          }
        ]
      }
    },
    "/v1/emails/{id}/verifications": {
      "post": {
        "tags": ["emails"],
        "operationId": "create_verification",
        "parameters": [
          {
            "name": "id",
            "in": "path",
            "description": "Email ID",
            "required": true,
            "schema": {
              "type": "string",
              "format": "uuid"
            }
          }
        ],
        "responses": {
          "200": {
            "description": "",
            "content": {
              "application/json": {
                "schema": {
                  "$ref": "#/components/schemas/OttTokenResponse"
                }
              }
            }
          },
          "401": {
            "description": "",
            "content": {
              "application/json": {
                "schema": {
                  "$ref": "#/components/schemas/ErrorResponse"
                }
              }
            }
          },
          "404": {
            "description": "Email not found or already verified",
            "content": {
              "application/json": {
                "schema": {
                  "$ref": "#/components/schemas/ErrorResponse"
                }
              }
            }
          }
        },
        "security": [
          {
            "BearerAuth": []
          }
        ]
      }
    },
    "/v1/invitations/{id}": {
      "get": {
        "tags": ["invitations"],
        "operationId": "view_invitation",
        "parameters": [
          {
            "name": "id",
            "in": "path",
            "description": "Invitation ID",
            "required": true,
            "schema": {
              "type": "string",
              "format": "uuid"
            }
          },
          {
            "name": "token",
            "in": "query",
            "description": "Plaintext invitation token",
            "required": true,
            "schema": {
              "type": "string"
            }
          }
        ],
        "responses": {
          "200": {
            "description": "",
            "content": {
              "application/json": {
                "schema": {
                  "$ref": "#/components/schemas/InvitationViewResponse"
                }
              }
            }
          },
          "404": {
            "description": "",
            "content": {
              "application/json": {
                "schema": {
                  "$ref": "#/components/schemas/ErrorResponse"
                }
              }
            }
          }
        }
      }
    },
    "/v1/invitations/{id}/acceptances": {
      "post": {
        "tags": ["invitations"],
        "operationId": "accept_invitation",
        "parameters": [
          {
            "name": "id",
            "in": "path",
            "description": "Invitation ID",
            "required": true,
            "schema": {
              "type": "string",
              "format": "uuid"
            }
          },
          {
            "name": "token",
            "in": "query",
            "description": "Plaintext invitation token",
            "required": true,
            "schema": {
              "type": "string"
            }
          }
        ],
        "responses": {
          "204": {
            "description": ""
          },
          "404": {
            "description": "Invitation not found or expired",
            "content": {
              "application/json": {
                "schema": {
                  "$ref": "#/components/schemas/ErrorResponse"
                }
              }
            }
          },
          "409": {
            "description": "Already a member",
            "content": {
              "application/json": {
                "schema": {
                  "$ref": "#/components/schemas/ErrorResponse"
                }
              }
            }
          }
        },
        "security": [
          {
            "BearerAuth": []
          }
        ]
      }
    },
    "/v1/invitations/{id}/declinations": {
      "post": {
        "tags": ["invitations"],
        "operationId": "decline_invitation",
        "parameters": [
          {
            "name": "id",
            "in": "path",
            "description": "Invitation ID",
            "required": true,
            "schema": {
              "type": "string",
              "format": "uuid"
            }
          },
          {
            "name": "token",
            "in": "query",
            "description": "Plaintext invitation token",
            "required": true,
            "schema": {
              "type": "string"
            }
          }
        ],
        "responses": {
          "204": {
            "description": ""
          },
          "404": {
            "description": "Invitation not found or expired",
            "content": {
              "application/json": {
                "schema": {
                  "$ref": "#/components/schemas/ErrorResponse"
                }
              }
            }
          }
        }
      }
    },
    "/v1/jwks.json": {
      "get": {
        "tags": ["system"],
        "operationId": "jwks",
        "responses": {
          "200": {
            "description": "",
            "headers": {
              "Cache-Control": {
                "schema": {
                  "type": "string"
                },
                "description": "public, max-age=3600, must-revalidate"
              }
            },
            "content": {
              "application/json": {
                "schema": {
                  "$ref": "#/components/schemas/JwkSet"
                }
              }
            }
          }
        }
      }
    },
    "/v1/magic-links": {
      "post": {
        "tags": ["magic-links"],
        "operationId": "create_magic_link",
        "requestBody": {
          "content": {
            "application/json": {
              "schema": {
                "$ref": "#/components/schemas/MagicLinkRequest"
              }
            }
          },
          "required": true
        },
        "responses": {
          "200": {
            "description": "",
            "content": {
              "application/json": {
                "schema": {
                  "$ref": "#/components/schemas/MagicLinkResponse"
                }
              }
            }
          },
          "404": {
            "description": "No account with that email",
            "content": {
              "application/json": {
                "schema": {
                  "$ref": "#/components/schemas/ErrorResponse"
                }
              }
            }
          }
        }
      }
    },
    "/v1/oauth/apple/callback": {
      "post": {
        "tags": ["oauth"],
        "operationId": "apple_callback",
        "requestBody": {
          "content": {
            "application/x-www-form-urlencoded": {
              "schema": {
                "$ref": "#/components/schemas/AppleCallbackForm"
              }
            }
          },
          "required": true
        },
        "responses": {
          "302": {
            "description": "Redirect to redirect_url with token and expires_at query params"
          },
          "400": {
            "description": "Invalid state or Apple error",
            "content": {
              "application/json": {
                "schema": {
                  "$ref": "#/components/schemas/ErrorResponse"
                }
              }
            }
          }
        }
      }
    },
    "/v1/oauth/{provider}": {
      "get": {
        "tags": ["oauth"],
        "operationId": "authorize",
        "parameters": [
          {
            "name": "provider",
            "in": "path",
            "description": "OAuth provider slug, e.g. `github`, `google`",
            "required": true,
            "schema": {
              "type": "string"
            }
          },
          {
            "name": "redirect_url",
            "in": "query",
            "description": "URL to redirect to after authentication",
            "required": true,
            "schema": {
              "type": "string"
            }
          }
        ],
        "responses": {
          "302": {
            "description": "Redirect to OAuth provider"
          },
          "400": {
            "description": "Provider not configured",
            "content": {
              "application/json": {
                "schema": {
                  "$ref": "#/components/schemas/ErrorResponse"
                }
              }
            }
          }
        }
      }
    },
    "/v1/oauth/{provider}/callback": {
      "get": {
        "tags": ["oauth"],
        "operationId": "callback",
        "parameters": [
          {
            "name": "provider",
            "in": "path",
            "description": "OAuth provider slug",
            "required": true,
            "schema": {
              "type": "string"
            }
          },
          {
            "name": "code",
            "in": "query",
            "description": "Authorization code from provider",
            "required": true,
            "schema": {
              "type": "string"
            }
          },
          {
            "name": "state",
            "in": "query",
            "description": "PKCE state JWT",
            "required": true,
            "schema": {
              "type": "string"
            }
          }
        ],
        "responses": {
          "302": {
            "description": "Redirect to redirect_url with token and expires_at query params"
          },
          "400": {
            "description": "Invalid state or provider error",
            "content": {
              "application/json": {
                "schema": {
                  "$ref": "#/components/schemas/ErrorResponse"
                }
              }
            }
          }
        }
      }
    },
    "/v1/orgs": {
      "get": {
        "tags": ["orgs"],
        "operationId": "list_orgs",
        "responses": {
          "200": {
            "description": "",
            "content": {
              "application/json": {
                "schema": {
                  "$ref": "#/components/schemas/OrgsResponse"
                }
              }
            }
          }
        },
        "security": [
          {
            "BearerAuth": []
          }
        ]
      },
      "post": {
        "tags": ["orgs"],
        "operationId": "create_org",
        "requestBody": {
          "content": {
            "application/json": {
              "schema": {
                "$ref": "#/components/schemas/CreateOrgRequest"
              }
            }
          },
          "required": true
        },
        "responses": {
          "201": {
            "description": "",
            "content": {
              "application/json": {
                "schema": {
                  "$ref": "#/components/schemas/OrgResponse"
                }
              }
            }
          },
          "409": {
            "description": "Slug already taken",
            "content": {
              "application/json": {
                "schema": {
                  "$ref": "#/components/schemas/ErrorResponse"
                }
              }
            }
          }
        },
        "security": [
          {
            "BearerAuth": []
          }
        ]
      }
    },
    "/v1/orgs/{id}": {
      "get": {
        "tags": ["orgs"],
        "operationId": "get_org",
        "parameters": [
          {
            "name": "id",
            "in": "path",
            "description": "Org ID",
            "required": true,
            "schema": {
              "type": "string",
              "format": "uuid"
            }
          }
        ],
        "responses": {
          "200": {
            "description": "",
            "content": {
              "application/json": {
                "schema": {
                  "$ref": "#/components/schemas/OrgResponse"
                }
              }
            }
          },
          "403": {
            "description": "",
            "content": {
              "application/json": {
                "schema": {
                  "$ref": "#/components/schemas/ErrorResponse"
                }
              }
            }
          },
          "404": {
            "description": "",
            "content": {
              "application/json": {
                "schema": {
                  "$ref": "#/components/schemas/ErrorResponse"
                }
              }
            }
          }
        },
        "security": [
          {
            "BearerAuth": []
          }
        ]
      },
      "delete": {
        "tags": ["orgs"],
        "operationId": "delete_org",
        "parameters": [
          {
            "name": "id",
            "in": "path",
            "description": "Org ID",
            "required": true,
            "schema": {
              "type": "string",
              "format": "uuid"
            }
          }
        ],
        "responses": {
          "204": {
            "description": ""
          },
          "403": {
            "description": "",
            "content": {
              "application/json": {
                "schema": {
                  "$ref": "#/components/schemas/ErrorResponse"
                }
              }
            }
          },
          "404": {
            "description": "",
            "content": {
              "application/json": {
                "schema": {
                  "$ref": "#/components/schemas/ErrorResponse"
                }
              }
            }
          },
          "409": {
            "description": "Cannot delete personal org",
            "content": {
              "application/json": {
                "schema": {
                  "$ref": "#/components/schemas/ErrorResponse"
                }
              }
            }
          }
        },
        "security": [
          {
            "BearerAuth": []
          }
        ]
      },
      "patch": {
        "tags": ["orgs"],
        "operationId": "update_org",
        "parameters": [
          {
            "name": "id",
            "in": "path",
            "description": "Org ID",
            "required": true,
            "schema": {
              "type": "string",
              "format": "uuid"
            }
          }
        ],
        "requestBody": {
          "content": {
            "application/json": {
              "schema": {
                "$ref": "#/components/schemas/UpdateOrgRequest"
              }
            }
          },
          "required": true
        },
        "responses": {
          "200": {
            "description": "",
            "content": {
              "application/json": {
                "schema": {
                  "$ref": "#/components/schemas/OrgResponse"
                }
              }
            }
          },
          "403": {
            "description": "",
            "content": {
              "application/json": {
                "schema": {
                  "$ref": "#/components/schemas/ErrorResponse"
                }
              }
            }
          },
          "404": {
            "description": "",
            "content": {
              "application/json": {
                "schema": {
                  "$ref": "#/components/schemas/ErrorResponse"
                }
              }
            }
          },
          "409": {
            "description": "Slug already taken",
            "content": {
              "application/json": {
                "schema": {
                  "$ref": "#/components/schemas/ErrorResponse"
                }
              }
            }
          }
        },
        "security": [
          {
            "BearerAuth": []
          }
        ]
      }
    },
    "/v1/orgs/{id}/invitations": {
      "get": {
        "tags": ["orgs"],
        "operationId": "list_invitations",
        "parameters": [
          {
            "name": "id",
            "in": "path",
            "description": "Org ID",
            "required": true,
            "schema": {
              "type": "string",
              "format": "uuid"
            }
          }
        ],
        "responses": {
          "200": {
            "description": "",
            "content": {
              "application/json": {
                "schema": {
                  "$ref": "#/components/schemas/InvitationsResponse"
                }
              }
            }
          },
          "403": {
            "description": "",
            "content": {
              "application/json": {
                "schema": {
                  "$ref": "#/components/schemas/ErrorResponse"
                }
              }
            }
          }
        },
        "security": [
          {
            "BearerAuth": []
          }
        ]
      },
      "post": {
        "tags": ["orgs"],
        "operationId": "create_invitation",
        "parameters": [
          {
            "name": "id",
            "in": "path",
            "description": "Org ID",
            "required": true,
            "schema": {
              "type": "string",
              "format": "uuid"
            }
          }
        ],
        "requestBody": {
          "content": {
            "application/json": {
              "schema": {
                "$ref": "#/components/schemas/CreateInvitationRequest"
              }
            }
          },
          "required": true
        },
        "responses": {
          "201": {
            "description": "",
            "content": {
              "application/json": {
                "schema": {
                  "$ref": "#/components/schemas/InvitationResponse"
                }
              }
            }
          },
          "403": {
            "description": "",
            "content": {
              "application/json": {
                "schema": {
                  "$ref": "#/components/schemas/ErrorResponse"
                }
              }
            }
          },
          "409": {
            "description": "Pending invite for this email already exists",
            "content": {
              "application/json": {
                "schema": {
                  "$ref": "#/components/schemas/ErrorResponse"
                }
              }
            }
          }
        },
        "security": [
          {
            "BearerAuth": []
          }
        ]
      }
    },
    "/v1/orgs/{id}/invitations/{inv_id}": {
      "delete": {
        "tags": ["orgs"],
        "operationId": "revoke_invitation",
        "parameters": [
          {
            "name": "id",
            "in": "path",
            "description": "Org ID",
            "required": true,
            "schema": {
              "type": "string",
              "format": "uuid"
            }
          },
          {
            "name": "inv_id",
            "in": "path",
            "description": "Invitation ID",
            "required": true,
            "schema": {
              "type": "string",
              "format": "uuid"
            }
          }
        ],
        "responses": {
          "204": {
            "description": ""
          },
          "403": {
            "description": "",
            "content": {
              "application/json": {
                "schema": {
                  "$ref": "#/components/schemas/ErrorResponse"
                }
              }
            }
          },
          "404": {
            "description": "",
            "content": {
              "application/json": {
                "schema": {
                  "$ref": "#/components/schemas/ErrorResponse"
                }
              }
            }
          }
        },
        "security": [
          {
            "BearerAuth": []
          }
        ]
      }
    },
    "/v1/orgs/{id}/members": {
      "get": {
        "tags": ["orgs"],
        "operationId": "list_members",
        "parameters": [
          {
            "name": "id",
            "in": "path",
            "description": "Org ID",
            "required": true,
            "schema": {
              "type": "string",
              "format": "uuid"
            }
          }
        ],
        "responses": {
          "200": {
            "description": "",
            "content": {
              "application/json": {
                "schema": {
                  "$ref": "#/components/schemas/MembersResponse"
                }
              }
            }
          },
          "403": {
            "description": "",
            "content": {
              "application/json": {
                "schema": {
                  "$ref": "#/components/schemas/ErrorResponse"
                }
              }
            }
          },
          "404": {
            "description": "",
            "content": {
              "application/json": {
                "schema": {
                  "$ref": "#/components/schemas/ErrorResponse"
                }
              }
            }
          }
        },
        "security": [
          {
            "BearerAuth": []
          }
        ]
      }
    },
    "/v1/orgs/{id}/members/{member_id}": {
      "delete": {
        "tags": ["orgs"],
        "operationId": "remove_member",
        "parameters": [
          {
            "name": "id",
            "in": "path",
            "description": "Org ID",
            "required": true,
            "schema": {
              "type": "string",
              "format": "uuid"
            }
          },
          {
            "name": "member_id",
            "in": "path",
            "description": "User ID of the member",
            "required": true,
            "schema": {
              "type": "string",
              "format": "uuid"
            }
          }
        ],
        "responses": {
          "204": {
            "description": ""
          },
          "403": {
            "description": "",
            "content": {
              "application/json": {
                "schema": {
                  "$ref": "#/components/schemas/ErrorResponse"
                }
              }
            }
          },
          "404": {
            "description": "",
            "content": {
              "application/json": {
                "schema": {
                  "$ref": "#/components/schemas/ErrorResponse"
                }
              }
            }
          },
          "409": {
            "description": "Would remove last owner",
            "content": {
              "application/json": {
                "schema": {
                  "$ref": "#/components/schemas/ErrorResponse"
                }
              }
            }
          }
        },
        "security": [
          {
            "BearerAuth": []
          }
        ]
      },
      "patch": {
        "tags": ["orgs"],
        "operationId": "update_member",
        "parameters": [
          {
            "name": "id",
            "in": "path",
            "description": "Org ID",
            "required": true,
            "schema": {
              "type": "string",
              "format": "uuid"
            }
          },
          {
            "name": "member_id",
            "in": "path",
            "description": "User ID of the member",
            "required": true,
            "schema": {
              "type": "string",
              "format": "uuid"
            }
          }
        ],
        "requestBody": {
          "content": {
            "application/json": {
              "schema": {
                "$ref": "#/components/schemas/UpdateMemberRequest"
              }
            }
          },
          "required": true
        },
        "responses": {
          "204": {
            "description": ""
          },
          "403": {
            "description": "",
            "content": {
              "application/json": {
                "schema": {
                  "$ref": "#/components/schemas/ErrorResponse"
                }
              }
            }
          },
          "404": {
            "description": "",
            "content": {
              "application/json": {
                "schema": {
                  "$ref": "#/components/schemas/ErrorResponse"
                }
              }
            }
          },
          "409": {
            "description": "Would remove last owner",
            "content": {
              "application/json": {
                "schema": {
                  "$ref": "#/components/schemas/ErrorResponse"
                }
              }
            }
          }
        },
        "security": [
          {
            "BearerAuth": []
          }
        ]
      }
    },
    "/v1/passkey-authentications": {
      "post": {
        "tags": ["passkeys"],
        "operationId": "begin_passkey_authentication",
        "responses": {
          "200": {
            "description": "",
            "content": {
              "application/json": {
                "schema": {
                  "$ref": "#/components/schemas/BeginResponse"
                }
              }
            }
          }
        }
      }
    },
    "/v1/passkey-registrations": {
      "post": {
        "tags": ["passkeys"],
        "operationId": "begin_passkey_registration",
        "responses": {
          "200": {
            "description": "",
            "content": {
              "application/json": {
                "schema": {
                  "$ref": "#/components/schemas/BeginResponse"
                }
              }
            }
          },
          "401": {
            "description": "",
            "content": {
              "application/json": {
                "schema": {
                  "$ref": "#/components/schemas/ErrorResponse"
                }
              }
            }
          }
        },
        "security": [
          {
            "BearerAuth": []
          }
        ]
      }
    },
    "/v1/passkeys": {
      "get": {
        "tags": ["passkey"],
        "operationId": "list_passkeys",
        "responses": {
          "200": {
            "description": "",
            "content": {
              "application/json": {
                "schema": {
                  "type": "array",
                  "items": {
                    "$ref": "#/components/schemas/CredentialRecord"
                  }
                }
              }
            }
          },
          "401": {
            "description": "",
            "content": {
              "application/json": {
                "schema": {
                  "$ref": "#/components/schemas/ErrorResponse"
                }
              }
            }
          }
        },
        "security": [
          {
            "BearerAuth": []
          }
        ]
      },
      "post": {
        "tags": ["passkeys"],
        "operationId": "create_passkey",
        "requestBody": {
          "content": {
            "application/json": {
              "schema": {
                "$ref": "#/components/schemas/FinishRegistrationRequest"
              }
            }
          },
          "required": true
        },
        "responses": {
          "201": {
            "description": "",
            "content": {
              "application/json": {
                "schema": {
                  "$ref": "#/components/schemas/RegisteredCredential"
                }
              }
            }
          },
          "401": {
            "description": "",
            "content": {
              "application/json": {
                "schema": {
                  "$ref": "#/components/schemas/ErrorResponse"
                }
              }
            }
          }
        },
        "security": [
          {
            "BearerAuth": []
          }
        ]
      }
    },
    "/v1/passkeys/{id}": {
      "delete": {
        "tags": ["passkeys"],
        "operationId": "delete_passkey",
        "parameters": [
          {
            "name": "id",
            "in": "path",
            "description": "Credential ID",
            "required": true,
            "schema": {
              "type": "string",
              "format": "uuid"
            }
          }
        ],
        "responses": {
          "204": {
            "description": "Credential deleted"
          },
          "401": {
            "description": "",
            "content": {
              "application/json": {
                "schema": {
                  "$ref": "#/components/schemas/ErrorResponse"
                }
              }
            }
          }
        },
        "security": [
          {
            "BearerAuth": []
          }
        ]
      },
      "patch": {
        "tags": ["passkeys"],
        "operationId": "update_passkey",
        "parameters": [
          {
            "name": "id",
            "in": "path",
            "description": "Credential ID",
            "required": true,
            "schema": {
              "type": "string",
              "format": "uuid"
            }
          }
        ],
        "requestBody": {
          "content": {
            "application/json": {
              "schema": {
                "$ref": "#/components/schemas/UpdateCredentialRequest"
              }
            }
          },
          "required": true
        },
        "responses": {
          "204": {
            "description": "Credential updated"
          },
          "401": {
            "description": "",
            "content": {
              "application/json": {
                "schema": {
                  "$ref": "#/components/schemas/ErrorResponse"
                }
              }
            }
          }
        },
        "security": [
          {
            "BearerAuth": []
          }
        ]
      }
    },
    "/v1/password-resets": {
      "post": {
        "tags": ["password-resets"],
        "operationId": "create_password_reset",
        "requestBody": {
          "content": {
            "application/json": {
              "schema": {
                "$ref": "#/components/schemas/PasswordResetRequest"
              }
            }
          },
          "required": true
        },
        "responses": {
          "200": {
            "description": "",
            "content": {
              "application/json": {
                "schema": {
                  "$ref": "#/components/schemas/PasswordResetResponse"
                }
              }
            }
          },
          "404": {
            "description": "No account with that email or no password identity",
            "content": {
              "application/json": {
                "schema": {
                  "$ref": "#/components/schemas/ErrorResponse"
                }
              }
            }
          }
        }
      }
    },
    "/v1/sessions": {
      "get": {
        "tags": ["sessions"],
        "operationId": "list_sessions",
        "responses": {
          "200": {
            "description": "",
            "content": {
              "application/json": {
                "schema": {
                  "$ref": "#/components/schemas/SessionsResponse"
                }
              }
            }
          },
          "401": {
            "description": "",
            "content": {
              "application/json": {
                "schema": {
                  "$ref": "#/components/schemas/ErrorResponse"
                }
              }
            }
          }
        },
        "security": [
          {
            "BearerAuth": []
          }
        ]
      },
      "post": {
        "tags": ["sessions"],
        "operationId": "login",
        "requestBody": {
          "content": {
            "application/json": {
              "schema": {
                "$ref": "#/components/schemas/LoginRequest"
              }
            }
          },
          "required": true
        },
        "responses": {
          "200": {
            "description": "MFA step-up required",
            "content": {
              "application/json": {
                "schema": {
                  "$ref": "#/components/schemas/StepUpResponse"
                }
              }
            }
          },
          "201": {
            "description": "Session created",
            "content": {
              "application/json": {
                "schema": {
                  "$ref": "#/components/schemas/AuthResponse"
                }
              }
            }
          },
          "401": {
            "description": "Invalid credentials or token",
            "content": {
              "application/json": {
                "schema": {
                  "$ref": "#/components/schemas/ErrorResponse"
                }
              }
            }
          },
          "422": {
            "description": "Password validation failed",
            "content": {
              "application/json": {
                "schema": {
                  "$ref": "#/components/schemas/ErrorResponse"
                }
              }
            }
          }
        }
      }
    },
    "/v1/sessions/current": {
      "get": {
        "tags": ["sessions"],
        "operationId": "get_current",
        "responses": {
          "200": {
            "description": "",
            "content": {
              "application/json": {
                "schema": {
                  "$ref": "#/components/schemas/CurrentSessionResponse"
                }
              }
            }
          },
          "401": {
            "description": "",
            "content": {
              "application/json": {
                "schema": {
                  "$ref": "#/components/schemas/ErrorResponse"
                }
              }
            }
          },
          "404": {
            "description": "",
            "content": {
              "application/json": {
                "schema": {
                  "$ref": "#/components/schemas/ErrorResponse"
                }
              }
            }
          }
        },
        "security": [
          {
            "BearerAuth": []
          }
        ]
      },
      "delete": {
        "tags": ["sessions"],
        "operationId": "delete_current",
        "responses": {
          "204": {
            "description": "Session revoked"
          },
          "401": {
            "description": "",
            "content": {
              "application/json": {
                "schema": {
                  "$ref": "#/components/schemas/ErrorResponse"
                }
              }
            }
          }
        },
        "security": [
          {
            "BearerAuth": []
          }
        ]
      }
    },
    "/v1/sessions/{id}": {
      "delete": {
        "tags": ["sessions"],
        "operationId": "delete_by_id",
        "parameters": [
          {
            "name": "id",
            "in": "path",
            "description": "Session ID",
            "required": true,
            "schema": {
              "type": "string",
              "format": "uuid"
            }
          }
        ],
        "responses": {
          "204": {
            "description": "Session revoked"
          },
          "401": {
            "description": "",
            "content": {
              "application/json": {
                "schema": {
                  "$ref": "#/components/schemas/ErrorResponse"
                }
              }
            }
          },
          "404": {
            "description": "",
            "content": {
              "application/json": {
                "schema": {
                  "$ref": "#/components/schemas/ErrorResponse"
                }
              }
            }
          }
        },
        "security": [
          {
            "BearerAuth": []
          }
        ]
      }
    },
    "/v1/tokens": {
      "post": {
        "tags": ["tokens"],
        "summary": "POST /v1/tokens — issue a short-lived JWT access token.\nRequires `jwt_enabled = true` in app_config; returns 400 otherwise.",
        "operationId": "issue",
        "responses": {
          "200": {
            "description": "",
            "content": {
              "application/json": {
                "schema": {
                  "$ref": "#/components/schemas/TokenResponse"
                }
              }
            }
          },
          "400": {
            "description": "JWT not enabled",
            "content": {
              "application/json": {
                "schema": {
                  "$ref": "#/components/schemas/ErrorResponse"
                }
              }
            }
          },
          "401": {
            "description": "",
            "content": {
              "application/json": {
                "schema": {
                  "$ref": "#/components/schemas/ErrorResponse"
                }
              }
            }
          }
        },
        "security": [
          {
            "BearerAuth": []
          }
        ]
      }
    },
    "/v1/totp": {
      "post": {
        "tags": ["totp"],
        "operationId": "begin_enrollment",
        "responses": {
          "200": {
            "description": "",
            "content": {
              "application/json": {
                "schema": {
                  "$ref": "#/components/schemas/EnrollmentResponse"
                }
              }
            }
          },
          "401": {
            "description": "",
            "content": {
              "application/json": {
                "schema": {
                  "$ref": "#/components/schemas/ErrorResponse"
                }
              }
            }
          }
        },
        "security": [
          {
            "BearerAuth": []
          }
        ]
      },
      "delete": {
        "tags": ["totp"],
        "operationId": "disable",
        "responses": {
          "204": {
            "description": "TOTP disabled"
          },
          "401": {
            "description": "",
            "content": {
              "application/json": {
                "schema": {
                  "$ref": "#/components/schemas/ErrorResponse"
                }
              }
            }
          }
        },
        "security": [
          {
            "BearerAuth": []
          }
        ]
      }
    },
    "/v1/totp/confirmations": {
      "post": {
        "tags": ["totp"],
        "operationId": "confirm_enrollment",
        "requestBody": {
          "content": {
            "application/json": {
              "schema": {
                "$ref": "#/components/schemas/ConfirmRequest"
              }
            }
          },
          "required": true
        },
        "responses": {
          "204": {
            "description": "TOTP enrollment confirmed"
          },
          "401": {
            "description": "",
            "content": {
              "application/json": {
                "schema": {
                  "$ref": "#/components/schemas/ErrorResponse"
                }
              }
            }
          }
        },
        "security": [
          {
            "BearerAuth": []
          }
        ]
      }
    },
    "/v1/users": {
      "post": {
        "tags": ["users"],
        "operationId": "signup",
        "requestBody": {
          "content": {
            "application/json": {
              "schema": {
                "$ref": "#/components/schemas/SignupRequest"
              }
            }
          },
          "required": true
        },
        "responses": {
          "201": {
            "description": "",
            "content": {
              "application/json": {
                "schema": {
                  "$ref": "#/components/schemas/AuthResponse"
                }
              }
            }
          },
          "409": {
            "description": "Email already registered",
            "content": {
              "application/json": {
                "schema": {
                  "$ref": "#/components/schemas/ErrorResponse"
                }
              }
            }
          },
          "422": {
            "description": "Password validation failed",
            "content": {
              "application/json": {
                "schema": {
                  "$ref": "#/components/schemas/ErrorResponse"
                }
              }
            }
          }
        }
      }
    },
    "/v1/users/me": {
      "get": {
        "tags": ["users"],
        "operationId": "get_me",
        "responses": {
          "200": {
            "description": "",
            "content": {
              "application/json": {
                "schema": {
                  "$ref": "#/components/schemas/MeResponse"
                }
              }
            }
          },
          "401": {
            "description": "",
            "content": {
              "application/json": {
                "schema": {
                  "$ref": "#/components/schemas/ErrorResponse"
                }
              }
            }
          }
        },
        "security": [
          {
            "BearerAuth": []
          }
        ]
      },
      "patch": {
        "tags": ["users"],
        "operationId": "update_me",
        "requestBody": {
          "content": {
            "application/json": {
              "schema": {
                "$ref": "#/components/schemas/UpdateUser"
              }
            }
          },
          "required": true
        },
        "responses": {
          "200": {
            "description": "",
            "content": {
              "application/json": {
                "schema": {
                  "$ref": "#/components/schemas/MeResponse"
                }
              }
            }
          },
          "401": {
            "description": "",
            "content": {
              "application/json": {
                "schema": {
                  "$ref": "#/components/schemas/ErrorResponse"
                }
              }
            }
          },
          "404": {
            "description": "",
            "content": {
              "application/json": {
                "schema": {
                  "$ref": "#/components/schemas/ErrorResponse"
                }
              }
            }
          }
        },
        "security": [
          {
            "BearerAuth": []
          }
        ]
      }
    }
  },
  "components": {
    "schemas": {
      "AddRequest": {
        "type": "object",
        "required": ["email"],
        "properties": {
          "email": {
            "type": "string"
          }
        }
      },
      "AppleCallbackForm": {
        "type": "object",
        "required": ["code", "state"],
        "properties": {
          "code": {
            "type": "string"
          },
          "state": {
            "type": "string"
          },
          "user": {
            "type": ["string", "null"]
          }
        }
      },
      "AuthResponse": {
        "type": "object",
        "required": ["user", "email", "org", "session"],
        "properties": {
          "email": {
            "$ref": "#/components/schemas/EmailBody"
          },
          "org": {
            "$ref": "#/components/schemas/OrgBody"
          },
          "session": {
            "$ref": "#/components/schemas/SessionBody"
          },
          "user": {
            "$ref": "#/components/schemas/UserBody"
          }
        }
      },
      "AuthzSchema": {
        "type": "object",
        "required": ["version", "resources"],
        "properties": {
          "resources": {
            "type": "array",
            "items": {
              "$ref": "#/components/schemas/ResourceDef"
            }
          },
          "subject_types": {
            "type": "array",
            "items": {
              "type": "string"
            }
          },
          "version": {
            "type": "integer",
            "format": "int32",
            "minimum": 0
          }
        }
      },
      "BatchRequest": {
        "type": "object",
        "properties": {
          "deletes": {
            "type": "array",
            "items": {
              "$ref": "#/components/schemas/RelationRequest"
            }
          },
          "writes": {
            "type": "array",
            "items": {
              "$ref": "#/components/schemas/RelationRequest"
            }
          }
        }
      },
      "BatchResponse": {
        "type": "object",
        "required": ["written", "deleted"],
        "properties": {
          "deleted": {
            "type": "integer",
            "format": "int64",
            "minimum": 0
          },
          "written": {
            "type": "integer",
            "format": "int64",
            "minimum": 0
          }
        }
      },
      "BeginResponse": {
        "type": "object",
        "required": ["options", "state_token"],
        "properties": {
          "options": {
            "type": "object",
            "description": "WebAuthn options object — pass directly to the browser's WebAuthn API."
          },
          "state_token": {
            "type": "string",
            "description": "Opaque state token; include in the corresponding finish request."
          }
        }
      },
      "CheckResponse": {
        "type": "object",
        "required": ["allowed"],
        "properties": {
          "allowed": {
            "type": "boolean"
          }
        }
      },
      "ConfirmRequest": {
        "type": "object",
        "required": ["code"],
        "properties": {
          "code": {
            "type": "string"
          }
        }
      },
      "ConfirmVerificationRequest": {
        "type": "object",
        "required": ["token"],
        "properties": {
          "token": {
            "type": "string"
          }
        }
      },
      "ConfirmVerificationResponse": {
        "type": "object",
        "required": ["verified_at"],
        "properties": {
          "verified_at": {
            "type": "string",
            "format": "date-time"
          }
        }
      },
      "CreateInvitationRequest": {
        "type": "object",
        "required": ["role"],
        "properties": {
          "email": {
            "type": ["string", "null"]
          },
          "role": {
            "type": "string"
          }
        }
      },
      "CreateOrgRequest": {
        "type": "object",
        "required": ["name"],
        "properties": {
          "metadata": {},
          "name": {
            "type": "string"
          },
          "slug": {
            "type": ["string", "null"]
          }
        }
      },
      "CredentialRecord": {
        "type": "object",
        "required": ["id", "created_at"],
        "properties": {
          "created_at": {
            "type": "string",
            "format": "date-time"
          },
          "id": {
            "type": "string",
            "format": "uuid"
          },
          "last_used_at": {
            "type": ["string", "null"],
            "format": "date-time"
          },
          "nickname": {
            "type": ["string", "null"]
          }
        }
      },
      "CurrentSessionResponse": {
        "type": "object",
        "required": ["id", "token_id", "created_at", "expires_at"],
        "properties": {
          "created_at": {
            "type": "string",
            "format": "date-time"
          },
          "expires_at": {
            "type": "string",
            "format": "date-time"
          },
          "id": {
            "type": "string",
            "format": "uuid"
          },
          "ip_address": {
            "type": ["string", "null"]
          },
          "last_used_at": {
            "type": ["string", "null"],
            "format": "date-time"
          },
          "token_id": {
            "type": "string",
            "format": "uuid"
          },
          "user_agent": {
            "type": ["string", "null"]
          }
        }
      },
      "EmailBody": {
        "type": "object",
        "required": ["id", "email"],
        "properties": {
          "email": {
            "type": "string"
          },
          "id": {
            "type": "string",
            "format": "uuid"
          },
          "verified_at": {
            "type": ["string", "null"],
            "format": "date-time"
          }
        }
      },
      "EmailRecord": {
        "type": "object",
        "required": ["id", "email", "is_primary"],
        "properties": {
          "email": {
            "type": "string"
          },
          "id": {
            "type": "string",
            "format": "uuid"
          },
          "is_primary": {
            "type": "boolean"
          },
          "verified_at": {
            "type": ["string", "null"],
            "format": "date-time"
          }
        }
      },
      "EnrollmentResponse": {
        "type": "object",
        "required": [
          "factor_id",
          "secret_b32",
          "provisioning_uri",
          "qr_data_url",
          "recovery_codes"
        ],
        "properties": {
          "factor_id": {
            "type": "string",
            "format": "uuid"
          },
          "provisioning_uri": {
            "type": "string"
          },
          "qr_data_url": {
            "type": "string"
          },
          "recovery_codes": {
            "type": "array",
            "items": {
              "type": "string"
            }
          },
          "secret_b32": {
            "type": "string"
          }
        }
      },
      "ErrorBody": {
        "type": "object",
        "description": "Wire-format error body returned on all non-2xx responses.",
        "required": ["code", "message"],
        "properties": {
          "code": {
            "type": "string",
            "description": "Machine-readable error code, e.g. `\"invalid_credentials\"`."
          },
          "message": {
            "type": "string",
            "description": "Human-readable description."
          }
        }
      },
      "ErrorResponse": {
        "type": "object",
        "description": "Top-level error envelope for all API error responses.",
        "required": ["error"],
        "properties": {
          "error": {
            "$ref": "#/components/schemas/ErrorBody"
          }
        }
      },
      "ExpandResponse": {
        "type": "object",
        "required": ["subjects"],
        "properties": {
          "subjects": {
            "type": "array",
            "items": {
              "$ref": "#/components/schemas/ExpandSubject"
            }
          }
        }
      },
      "ExpandSubject": {
        "type": "object",
        "required": ["id", "relation"],
        "properties": {
          "id": {
            "type": "string"
          },
          "relation": {
            "type": "string"
          }
        }
      },
      "FinishRegistrationRequest": {
        "type": "object",
        "required": ["state_token", "credential"],
        "properties": {
          "credential": {
            "type": "object",
            "description": "WebAuthn `PublicKeyCredential` response from the browser."
          },
          "nickname": {
            "type": ["string", "null"]
          },
          "state_token": {
            "type": "string"
          }
        }
      },
      "HealthzResponse": {
        "type": "object",
        "required": ["status", "version"],
        "properties": {
          "status": {
            "type": "string"
          },
          "version": {
            "type": "string"
          }
        }
      },
      "HierarchyDef": {
        "type": "object",
        "required": ["parent_relation", "parent_resource"],
        "properties": {
          "parent_relation": {
            "type": "string",
            "description": "The relation name on this resource that points to parent objects."
          },
          "parent_resource": {
            "type": "string",
            "description": "The resource type of the parent."
          }
        }
      },
      "InvitationResponse": {
        "type": "object",
        "required": ["id", "org_id", "role", "created_at", "expires_at"],
        "properties": {
          "created_at": {
            "type": "string",
            "format": "date-time"
          },
          "email": {
            "type": ["string", "null"]
          },
          "expires_at": {
            "type": "string",
            "format": "date-time"
          },
          "id": {
            "type": "string",
            "format": "uuid"
          },
          "org_id": {
            "type": "string",
            "format": "uuid"
          },
          "role": {
            "type": "string"
          },
          "token": {
            "type": ["string", "null"],
            "description": "Plaintext token — only present on creation, never returned again."
          }
        }
      },
      "InvitationViewResponse": {
        "type": "object",
        "required": ["id", "org_id", "org_name", "role", "expires_at"],
        "properties": {
          "expires_at": {
            "type": "string",
            "format": "date-time"
          },
          "id": {
            "type": "string",
            "format": "uuid"
          },
          "org_id": {
            "type": "string",
            "format": "uuid"
          },
          "org_name": {
            "type": "string"
          },
          "role": {
            "type": "string"
          }
        }
      },
      "InvitationsResponse": {
        "type": "object",
        "required": ["invitations"],
        "properties": {
          "invitations": {
            "type": "array",
            "items": {
              "$ref": "#/components/schemas/InvitationResponse"
            }
          }
        }
      },
      "Jwk": {
        "type": "object",
        "required": ["kty", "crv", "kid", "use", "alg", "x"],
        "properties": {
          "alg": {
            "type": "string"
          },
          "crv": {
            "type": "string"
          },
          "kid": {
            "type": "string"
          },
          "kty": {
            "type": "string"
          },
          "use": {
            "type": "string"
          },
          "x": {
            "type": "string"
          }
        }
      },
      "JwkSet": {
        "type": "object",
        "required": ["keys"],
        "properties": {
          "keys": {
            "type": "array",
            "items": {
              "$ref": "#/components/schemas/Jwk"
            }
          }
        }
      },
      "LoginRequest": {
        "oneOf": [
          {
            "type": "object",
            "required": ["email", "password", "grant_type"],
            "properties": {
              "email": {
                "type": "string"
              },
              "grant_type": {
                "type": "string",
                "enum": ["password"]
              },
              "password": {
                "type": "string"
              }
            }
          },
          {
            "type": "object",
            "required": ["token", "grant_type"],
            "properties": {
              "grant_type": {
                "type": "string",
                "enum": ["magic_link"]
              },
              "token": {
                "type": "string"
              }
            }
          },
          {
            "type": "object",
            "required": ["token", "new_password", "grant_type"],
            "properties": {
              "grant_type": {
                "type": "string",
                "enum": ["password_reset"]
              },
              "new_password": {
                "type": "string"
              },
              "token": {
                "type": "string"
              }
            }
          },
          {
            "type": "object",
            "required": ["token", "grant_type"],
            "properties": {
              "grant_type": {
                "type": "string",
                "enum": ["email_change"]
              },
              "token": {
                "type": "string"
              }
            }
          },
          {
            "type": "object",
            "required": ["step_up_token", "code", "grant_type"],
            "properties": {
              "code": {
                "type": "string"
              },
              "grant_type": {
                "type": "string",
                "enum": ["totp_step_up"]
              },
              "step_up_token": {
                "type": "string"
              }
            }
          },
          {
            "type": "object",
            "required": ["step_up_token", "code", "grant_type"],
            "properties": {
              "code": {
                "type": "string"
              },
              "grant_type": {
                "type": "string",
                "enum": ["totp_recovery"]
              },
              "step_up_token": {
                "type": "string"
              }
            }
          },
          {
            "type": "object",
            "required": ["state_token", "credential", "grant_type"],
            "properties": {
              "credential": {
                "type": "object"
              },
              "grant_type": {
                "type": "string",
                "enum": ["passkey"]
              },
              "state_token": {
                "type": "string"
              }
            }
          }
        ]
      },
      "LookupResponse": {
        "type": "object",
        "required": ["object_ids"],
        "properties": {
          "next_cursor": {
            "type": ["string", "null"]
          },
          "object_ids": {
            "type": "array",
            "items": {
              "type": "string"
            }
          }
        }
      },
      "MagicLinkRequest": {
        "type": "object",
        "required": ["email"],
        "properties": {
          "email": {
            "type": "string"
          }
        }
      },
      "MagicLinkResponse": {
        "type": "object",
        "required": ["token", "expires_at"],
        "properties": {
          "expires_at": {
            "type": "string",
            "format": "date-time"
          },
          "token": {
            "type": "string",
            "description": "One-time token to exchange via `POST /v1/sessions` with `grant_type=magic_link`."
          }
        }
      },
      "MeResponse": {
        "type": "object",
        "required": ["user", "email", "org"],
        "properties": {
          "email": {
            "$ref": "#/components/schemas/EmailBody"
          },
          "org": {
            "$ref": "#/components/schemas/OrgBody"
          },
          "user": {
            "$ref": "#/components/schemas/UserBody"
          }
        }
      },
      "MemberResponse": {
        "type": "object",
        "required": ["user_id", "role", "joined_at"],
        "properties": {
          "joined_at": {
            "type": "string",
            "format": "date-time"
          },
          "role": {
            "type": "string"
          },
          "user_id": {
            "type": "string",
            "format": "uuid"
          }
        }
      },
      "MembersResponse": {
        "type": "object",
        "required": ["members"],
        "properties": {
          "members": {
            "type": "array",
            "items": {
              "$ref": "#/components/schemas/MemberResponse"
            }
          }
        }
      },
      "OrgBody": {
        "type": "object",
        "required": ["id", "name", "slug"],
        "properties": {
          "id": {
            "type": "string",
            "format": "uuid"
          },
          "name": {
            "type": "string"
          },
          "slug": {
            "type": "string"
          }
        }
      },
      "OrgResponse": {
        "type": "object",
        "required": ["id", "name", "slug", "metadata", "created_at"],
        "properties": {
          "created_at": {
            "type": "string",
            "format": "date-time"
          },
          "id": {
            "type": "string",
            "format": "uuid"
          },
          "metadata": {},
          "name": {
            "type": "string"
          },
          "slug": {
            "type": "string"
          }
        }
      },
      "OrgsResponse": {
        "type": "object",
        "required": ["orgs"],
        "properties": {
          "orgs": {
            "type": "array",
            "items": {
              "$ref": "#/components/schemas/OrgResponse"
            }
          }
        }
      },
      "OttTokenResponse": {
        "type": "object",
        "required": ["token", "expires_at"],
        "properties": {
          "expires_at": {
            "type": "string",
            "format": "date-time"
          },
          "token": {
            "type": "string",
            "description": "One-time token to use in the corresponding session grant."
          }
        }
      },
      "PasswordResetRequest": {
        "type": "object",
        "required": ["email"],
        "properties": {
          "email": {
            "type": "string"
          }
        }
      },
      "PasswordResetResponse": {
        "type": "object",
        "required": ["token", "expires_at"],
        "properties": {
          "expires_at": {
            "type": "string",
            "format": "date-time"
          },
          "token": {
            "type": "string",
            "description": "One-time token to exchange via `POST /v1/sessions` with `grant_type=password_reset`."
          }
        }
      },
      "RegisteredCredential": {
        "type": "object",
        "required": ["id", "created_at"],
        "properties": {
          "created_at": {
            "type": "string",
            "format": "date-time"
          },
          "id": {
            "type": "string",
            "format": "uuid"
          },
          "nickname": {
            "type": ["string", "null"]
          }
        }
      },
      "RelationObject": {
        "type": "object",
        "required": ["type", "id"],
        "properties": {
          "id": {
            "type": "string"
          },
          "type": {
            "type": "string"
          }
        }
      },
      "RelationRequest": {
        "type": "object",
        "required": ["object", "relation", "subject"],
        "properties": {
          "object": {
            "$ref": "#/components/schemas/RelationObject"
          },
          "relation": {
            "type": "string"
          },
          "subject": {
            "$ref": "#/components/schemas/RelationSubject"
          }
        }
      },
      "RelationSubject": {
        "type": "object",
        "required": ["id"],
        "properties": {
          "id": {
            "type": "string"
          },
          "relation": {
            "type": ["string", "null"]
          },
          "type": {
            "type": ["string", "null"]
          }
        }
      },
      "ResourceDef": {
        "type": "object",
        "required": ["name", "roles", "permissions"],
        "properties": {
          "hierarchy": {
            "oneOf": [
              {
                "type": "null"
              },
              {
                "$ref": "#/components/schemas/HierarchyDef"
              }
            ]
          },
          "name": {
            "type": "string"
          },
          "permissions": {
            "type": "object",
            "additionalProperties": {
              "type": "array",
              "items": {
                "type": "string"
              }
            },
            "propertyNames": {
              "type": "string"
            }
          },
          "role_hierarchy": {
            "type": "array",
            "items": {
              "$ref": "#/components/schemas/RoleEdge"
            }
          },
          "roles": {
            "type": "array",
            "items": {
              "type": "string"
            }
          }
        }
      },
      "RoleEdge": {
        "type": "object",
        "required": ["superior", "inferior"],
        "properties": {
          "inferior": {
            "type": "string"
          },
          "superior": {
            "type": "string"
          }
        }
      },
      "SessionBody": {
        "type": "object",
        "required": ["id", "token", "expires_at"],
        "properties": {
          "expires_at": {
            "type": "string",
            "format": "date-time"
          },
          "id": {
            "type": "string",
            "format": "uuid"
          },
          "token": {
            "type": "string",
            "description": "Opaque bearer token — store securely, transmit as `Authorization: Bearer <token>`."
          }
        }
      },
      "SessionListItem": {
        "type": "object",
        "required": ["id", "token_id", "created_at", "expires_at", "current"],
        "properties": {
          "created_at": {
            "type": "string",
            "format": "date-time"
          },
          "current": {
            "type": "boolean",
            "description": "Whether this is the caller's current session."
          },
          "expires_at": {
            "type": "string",
            "format": "date-time"
          },
          "id": {
            "type": "string",
            "format": "uuid"
          },
          "ip_address": {
            "type": ["string", "null"]
          },
          "last_used_at": {
            "type": ["string", "null"],
            "format": "date-time"
          },
          "token_id": {
            "type": "string",
            "format": "uuid"
          },
          "user_agent": {
            "type": ["string", "null"]
          }
        }
      },
      "SessionsResponse": {
        "type": "object",
        "required": ["sessions"],
        "properties": {
          "sessions": {
            "type": "array",
            "items": {
              "$ref": "#/components/schemas/SessionListItem"
            }
          }
        }
      },
      "SignupRequest": {
        "type": "object",
        "required": ["email", "password"],
        "properties": {
          "display_name": {
            "type": ["string", "null"]
          },
          "email": {
            "type": "string"
          },
          "password": {
            "type": "string"
          }
        }
      },
      "StepUpResponse": {
        "type": "object",
        "description": "Returned when the user has TOTP enrolled — caller must complete the step-up flow.",
        "required": ["step_up_required", "step_up_token"],
        "properties": {
          "step_up_required": {
            "type": "string",
            "description": "The MFA method required, e.g. `\"totp\"`."
          },
          "step_up_token": {
            "type": "string",
            "description": "Short-lived signed token to present when completing the step-up."
          }
        }
      },
      "TokenResponse": {
        "type": "object",
        "required": ["access_token", "token_type", "expires_in"],
        "properties": {
          "access_token": {
            "type": "string"
          },
          "expires_in": {
            "type": "integer",
            "format": "int32",
            "description": "Lifetime in seconds."
          },
          "token_type": {
            "type": "string"
          }
        }
      },
      "TraceResponse": {
        "type": "object",
        "required": ["allowed", "subjects"],
        "properties": {
          "allowed": {
            "type": "boolean"
          },
          "subjects": {
            "type": "array",
            "items": {
              "$ref": "#/components/schemas/ExpandSubject"
            }
          }
        }
      },
      "UpdateCredentialRequest": {
        "type": "object",
        "required": ["nickname"],
        "properties": {
          "nickname": {
            "type": "string"
          }
        }
      },
      "UpdateMemberRequest": {
        "type": "object",
        "required": ["role"],
        "properties": {
          "role": {
            "type": "string"
          }
        }
      },
      "UpdateOrgRequest": {
        "type": "object",
        "properties": {
          "metadata": {},
          "name": {
            "type": ["string", "null"]
          },
          "slug": {
            "type": ["string", "null"]
          }
        }
      },
      "UpdateUser": {
        "type": "object",
        "properties": {
          "image_url": {
            "type": ["string", "null"]
          },
          "display_name": {
            "type": ["string", "null"]
          }
        }
      },
      "UserBody": {
        "type": "object",
        "required": ["id", "created_at"],
        "properties": {
          "image_url": {
            "type": ["string", "null"]
          },
          "created_at": {
            "type": "string",
            "format": "date-time"
          },
          "display_name": {
            "type": ["string", "null"]
          },
          "id": {
            "type": "string",
            "format": "uuid"
          }
        }
      }
    },
    "securitySchemes": {
      "BearerAuth": {
        "type": "http",
        "scheme": "bearer",
        "bearerFormat": "session_<id>_<secret>"
      }
    }
  },
  "tags": [
    {
      "name": "system",
      "description": "Health and key material"
    },
    {
      "name": "users",
      "description": "User registration and profile"
    },
    {
      "name": "sessions",
      "description": "Session lifecycle and MFA step-up"
    },
    {
      "name": "tokens",
      "description": "JWT access token issuance"
    },
    {
      "name": "emails",
      "description": "Email management and verification"
    },
    {
      "name": "magic-links",
      "description": "Passwordless magic link auth"
    },
    {
      "name": "password-resets",
      "description": "Password reset flow"
    },
    {
      "name": "totp",
      "description": "TOTP enrollment and management"
    },
    {
      "name": "oauth",
      "description": "OAuth 2.0 provider login"
    },
    {
      "name": "passkeys",
      "description": "Passkey registration and authentication"
    },
    {
      "name": "orgs",
      "description": "Org management, membership, and invitations"
    },
    {
      "name": "invitations",
      "description": "Invitation accept and decline"
    }
  ]
}
